contact_test/__init__.py
contact_test-0.1.46.dist-info/METADATA
contact_test-0.1.46.dist-info/WHEEL
contact_test-0.1.46.dist-info/top_level.txt
contact_test-0.1.46.dist-info/RECORD
