Metadata-Version: 2.4
Name: contact_test
Version: 0.1.46
Summary: A dummy test package for PyPI testing
Author: CONTACT Software GmbH
License-Expression: MIT
Requires-Python: >=3.9
